{
  "data": {
    "type": "rentals",
    "id": "downtown-citadel",
    "attributes": {
      "title": "Downtown Citadel",
      "owner": "Yedikule Dungeons",
      "city": "Istanbul",
      "location": {
        "lat": 40.9937, 
        "lng": 28.9227
      },
      "category": "Apartment",
      "bedrooms": 3,
      "image": "https://images.pexels.com/photos/7492125/pexels-photo-7492125.jpeg",
      "description": "Convenience is at your doorstep with this charming downtown rental. Great restaurants and active night life are within a few feet."
    }
  }
}
